dna_designer2/__init__.py
dna_designer2/codons.py
dna_designer2/dev.py
dna_designer2-0.0.2.dist-info/METADATA
dna_designer2-0.0.2.dist-info/WHEEL
dna_designer2-0.0.2.dist-info/top_level.txt
dna_designer2-0.0.2.dist-info/RECORD
