Metadata-Version: 2.1
Name: dna-designer2
Version: 0.0.2
Summary: A DNA design package
Home-page: http://github.com/koeng101/dna_designer2
Author: Keoni Gandall
Author-email: koeng101@gmail.com
License: UNKNOWN
Platform: UNKNOWN
Classifier: Programming Language :: Python :: 3
Classifier: License :: OSI Approved :: MIT License
Classifier: Operating System :: OS Independent
Requires-Python: >=3.6
